prompt_debugger/__init__.py
prompt_debugger/analyzer.py
prompt_debugger/debugger.py
prompt_debugger/logger.py
prompt_debugger/prompt_checker.py
prompt_debugger-0.1.1.dist-info/licenses/LICENSE
prompt_debugger-0.1.1.dist-info/METADATA
prompt_debugger-0.1.1.dist-info/WHEEL
prompt_debugger-0.1.1.dist-info/top_level.txt
prompt_debugger-0.1.1.dist-info/RECORD
