Metadata-Version: 2.4
Name: prompt-debugger
Version: 0.1.1
Summary: Debug AI responses, understand failures, and get automatic improvement suggestions
Author: Mohamed Imthiyas
License: MIT
Project-URL: Homepage, https://github.com/yourusername/prompt-debugger
Project-URL: Repository, https://github.com/yourusername/prompt-debugger
Keywords: llm,ai,debugging,prompt-engineering
Classifier: Development Status :: 3 - Alpha
Classifier: Intended Audience :: Developers
Classifier: License :: OSI Approved :: MIT License
Classifier: Programming Language :: Python :: 3
Classifier: Programming Language :: Python :: 3.8
Classifier: Programming Language :: Python :: 3.9
Classifier: Programming Language :: Python :: 3.10
Classifier: Programming Language :: Python :: 3.11
Classifier: Programming Language :: Python :: 3.12
Classifier: Topic :: Software Development :: Libraries :: Python Modules
Classifier: Topic :: Software Development :: Debuggers
Requires-Python: >=3.8
License-File: LICENSE
Dynamic: license-file
Dynamic: requires-python
